deFIBrillator/__init__.py
deFIBrillator/beams/__init__.py
deFIBrillator/beams/beam.py
deFIBrillator/beams/ion_beams.py
deFIBrillator/fib/__init__.py
deFIBrillator/fib/fib.py
deFIBrillator/fib/helios_nanolab_g2.py
deFIBrillator/fib/resources.py
deFIBrillator/mill/__init__.py
deFIBrillator/mill/mill.py
deFIBrillator/pattern/__init__.py
deFIBrillator/pattern/pattern.py
deFIBrillator/redosing/__init__.py
deFIBrillator/redosing/redose.py
deFIBrillator/resources/__init__.py
deFIBrillator/resources/conversions.py
deFIBrillator/resources/enums.py
deFIBrillator/resources/functions.py
deFIBrillator/scan_styles/__init__.py
deFIBrillator/scan_styles/contour.py
deFIBrillator/shapes/__init__.py
deFIBrillator/shapes/circle.py
deFIBrillator/shapes/lattice.py
deFIBrillator/shapes/polygon.py
deFIBrillator/shapes/rectangle.py
deFIBrillator/shapes/regular_polygon.py
deFIBrillator/shapes/shape.py
deFIBrillator/shapes/text.py
defibrillator-0.0.5.dist-info/METADATA
defibrillator-0.0.5.dist-info/WHEEL
defibrillator-0.0.5.dist-info/licenses/LICENSE
defibrillator-0.0.5.dist-info/RECORD
