Metadata-Version: 2.4
Name: deFIBrillator
Version: 0.0.5
Summary: A package used to create beam paths for milling complex geometries using a focused ion beam system.
Project-URL: Homepage, https://github.com/pypa/sampleproject
Project-URL: Issues, https://github.com/pypa/sampleproject/issues
Author-email: Magnus Oscar Støleggen <mgnsoscar@gmail.com>
License-Expression: MIT
License-File: LICENSE
Classifier: Operating System :: OS Independent
Classifier: Programming Language :: Python :: 3
Requires-Python: >=3.11
Requires-Dist: matplotlib
Requires-Dist: numpy
Requires-Dist: shapely
